<annotation>
  <folder>Coin</folder>
  <filename>0488348bcc457d16.jpg</filename>
  <path>/home/ala/Bureau/BessmellahDataBase/OIDv4_ToolKit/OID/Dataset/train/Coin/0488348bcc457d16.jpg</path>
  <source>
    <database>Unknown</database>
  </source>
  <size>
    <width>1024</width>
    <height>683</height>
    <depth>3</depth>
  </size>
  <segmented>0</segmented>
  <object>
    <name>Coin</name>
    <pose>Unspecified</pose>
    <truncated>0</truncated>
    <difficult>0</difficult>
    <bndbox>
      <xmin>641</xmin>
      <ymin>288</ymin>
      <xmax>861</xmax>
      <ymax>417</ymax>
    </bndbox>
  </object>
  <object>
    <name>Coin</name>
    <pose>Unspecified</pose>
    <truncated>0</truncated>
    <difficult>0</difficult>
    <bndbox>
      <xmin>62</xmin>
      <ymin>0</ymin>
      <xmax>954</xmax>
      <ymax>617</ymax>
    </bndbox>
  </object>
</annotation>
